etcdgrpc/__init__.py
etcdgrpc/auth_pb2.py
etcdgrpc/kv_pb2.py
etcdgrpc/rpc_pb2.py
etcdgrpc/rpc_pb2_grpc.py
pyetcd/Balancer.py
pyetcd/Connection.py
pyetcd/EtcdClient.py
pyetcd/KV.py
pyetcd/__init__.py
test/Etcdclient_test.py
test/__init__.py
pyetcd3-1.0.0.dist-info/LICENSE
pyetcd3-1.0.0.dist-info/METADATA
pyetcd3-1.0.0.dist-info/WHEEL
pyetcd3-1.0.0.dist-info/top_level.txt
pyetcd3-1.0.0.dist-info/RECORD
